svy_sae.cpython-313-aarch64-linux-gnu.so
svy_sae.pyi
svy_sae-0.1.0.dist-info/METADATA
svy_sae-0.1.0.dist-info/WHEEL
svy_sae-0.1.0.dist-info/entry_points.txt
svy_sae-0.1.0.dist-info/top_level.txt
svy_sae-0.1.0.dist-info/RECORD
