Metadata-Version: 2.4
Name: svy-sae
Version: 0.1.0
Summary: Scalable Small Area Estimation with JAX
Author-email: Samplics LLC <msdiallo@samplics.org>
Keywords: sampling,sample,weighting,estimation,survey
Classifier: Programming Language :: Python :: Implementation :: CPython
Classifier: Programming Language :: Python :: 3.11
Classifier: Programming Language :: Python :: 3.12
Classifier: Programming Language :: Python :: 3.13
Classifier: Programming Language :: Python :: 3.14
Classifier: Development Status :: 4 - Beta
Classifier: Operating System :: OS Independent
Classifier: Topic :: Scientific/Engineering
Requires-Python: >=3.11
Requires-Dist: jax>=0.8.2
Requires-Dist: jaxlib>=0.8.2
Requires-Dist: scipy>=1.16.3
Requires-Dist: svy[report]>=0.0.10
Requires-Dist: tqdm>=4.67.1
